Metadata-Version: 2.4
Name: llama-index-readers-telegram
Version: 0.4.1
Summary: llama-index readers telegram integration
Author-email: Dias Kalkamanov <diicellman@gmail.com>
Maintainer: diicell
License-Expression: MIT
License-File: LICENSE
Requires-Python: <4.0,>=3.9
Requires-Dist: llama-index-core<0.15,>=0.13.0
Requires-Dist: telethon<2,>=1.33.1
